cache_to_disk/__init__.py
cache2disk-4.2.1.dist-info/METADATA
cache2disk-4.2.1.dist-info/WHEEL
cache2disk-4.2.1.dist-info/top_level.txt
cache2disk-4.2.1.dist-info/RECORD
