Metadata-Version: 2.4
Name: cache2disk
Version: 4.2.1
Summary: A powerful and robust Python decorator for caching function results to disk.
Home-page: https://github.com/Atakey/cache_to_disk
Author: Atakey
Author-email: Atakey <hhl_helonky@163.com>
License: MIT License
Project-URL: Homepage, https://github.com/Atakey/cache_to_disk
Project-URL: Bug Tracker, https://github.com/Atakey/cache_to_disk/issues
Keywords: cache,disk,decorator,performance,async,filelock
Classifier: Programming Language :: Python :: 3
Classifier: Programming Language :: Python :: 3.6
Classifier: Programming Language :: Python :: 3.7
Classifier: Programming Language :: Python :: 3.8
Classifier: Programming Language :: Python :: 3.9
Classifier: Programming Language :: Python :: 3.10
Classifier: Programming Language :: Python :: 3.11
Classifier: Programming Language :: Python :: 3.12
Classifier: License :: OSI Approved :: MIT License
Classifier: Operating System :: OS Independent
Classifier: Intended Audience :: Developers
Classifier: Topic :: Software Development :: Libraries :: Python Modules
Classifier: Topic :: Utilities
Requires-Python: >=3.6
Requires-Dist: orjson
Requires-Dist: filelock
Dynamic: author
Dynamic: home-page
Dynamic: requires-python
